{"cod":"200","message":0.2681,"cnt":40,"list":[{"dt":1542034800,"main":{"temp":9.53,"temp_min":9.53,"temp_max":11.76,"pressure":1029.6,"sea_level":1034.42,"grnd_level":1029.6,"humidity":85,"temp_kf":-2.22},"weather":[{"id":803,"main":"Clouds","description":"broken clouds","icon":"04n"}],"clouds":{"all":64},"wind":{"speed":3.93,"deg":180.001},"sys":{"pod":"n"},"dt_txt":"2018-11-12 15:00:00"},{"dt":1542045600,"main":{"temp":9.52,"temp_min":9.52,"temp_max":11.18,"pressure":1029.36,"sea_level":1034.21,"grnd_level":1029.36,"humidity":89,"temp_kf":-1.67},"weather":[{"id":803,"main":"Clouds","description":"broken clouds","icon":"04n"}],"clouds":{"all":80},"wind":{"speed":6.58,"deg":183},"sys":{"pod":"n"},"dt_txt":"2018-11-12 18:00:00"},{"dt":1542056400,"main":{"temp":10.22,"temp_min":10.22,"temp_max":11.33,"pressure":1028.45,"sea_level":1033.33,"grnd_level":1028.45,"humidity":90,"temp_kf":-1.11},"weather":[{"id":802,"main":"Clouds","description":"scattered clouds","icon":"03n"}],"clouds":{"all":44},"wind":{"speed":8.98,"deg":187.501},"sys":{"pod":"n"},"dt_txt":"2018-11-12 21:00:00"},{"dt":1542067200,"main":{"temp":10.48,"temp_min":10.48,"temp_max":11.03,"pressure":1028.06,"sea_level":1033.05,"grnd_level":1028.06,"humidity":93,"temp_kf":-0.56},"weather":[{"id":804,"main":"Clouds","description":"overcast clouds","icon":"04n"}],"clouds":{"all":92},"wind":{"speed":9.19,"deg":198},"sys":{"pod":"n"},"dt_txt":"2018-11-13 00:00:00"},{"dt":1542078000,"main":{"temp":10.4,"temp_min":10.4,"temp_max":10.4,"pressure":1027.63,"sea_level":1032.46,"grnd_level":1027.63,"humidity":96,"temp_kf":0},"weather":[{"id":803,"main":"Clouds","description":"broken clouds","icon":"04n"}],"clouds":{"all":80},"wind":{"speed":8.16,"deg":206.504},"sys":{"pod":"n"},"dt_txt":"2018-11-13 03:00:00"},{"dt":1542088800,"main":{"temp":10.42,"temp_min":10.42,"temp_max":10.42,"pressure":1027.64,"sea_level":1032.6,"grnd_level":1027.64,"humidity":96,"temp_kf":0},"weather":[{"id":804,"main":"Clouds","description":"overcast clouds","icon":"04n"}],"clouds":{"all":88},"wind":{"speed":6.61,"deg":218.001},"sys":{"pod":"n"},"dt_txt":"2018-11-13 06:00:00"},{"dt":1542099600,"main":{"temp":10.58,"temp_min":10.58,"temp_max":10.58,"pressure":1027.25,"sea_level":1032.08,"grnd_level":1027.25,"humidity":95,"temp_kf":0},"weather":[{"id":500,"main":"Rain","description":"light rain","icon":"10d"}],"clouds":{"all":88},"wind":{"speed":4.42,"deg":204.001},"rain":{"3h":0.025},"sys":{"pod":"d"},"dt_txt":"2018-11-13 09:00:00"},{"dt":1542110400,"main":{"temp":10.88,"temp_min":10.88,"temp_max":10.88,"pressure":1026.57,"sea_level":1031.38,"grnd_level":1026.57,"humidity":94,"temp_kf":0},"weather":[{"id":500,"main":"Rain","description":"light rain","icon":"10d"}],"clouds":{"all":92},"wind":{"speed":4.61,"deg":237.501},"rain":{"3h":1.195},"sys":{"pod":"d"},"dt_txt":"2018-11-13 12:00:00"},{"dt":1542121200,"main":{"temp":9.86,"temp_min":9.86,"temp_max":9.86,"pressure":1026.8,"sea_level":1031.6,"grnd_level":1026.8,"humidity":100,"temp_kf":0},"weather":[{"id":501,"main":"Rain","description":"moderate rain","icon":"10n"}],"clouds":{"all":92},"wind":{"speed":6.39,"deg":319.007},"rain":{"3h":4.9},"sys":{"pod":"n"},"dt_txt":"2018-11-13 15:00:00"},{"dt":1542132000,"main":{"temp":9.24,"temp_min":9.24,"temp_max":9.24,"pressure":1028.09,"sea_level":1032.99,"grnd_level":1028.09,"humidity":100,"temp_kf":0},"weather":[{"id":500,"main":"Rain","description":"light rain","icon":"10n"}],"clouds":{"all":92},"wind":{"speed":6.18,"deg":272.501},"rain":{"3h":0.695},"sys":{"pod":"n"},"dt_txt":"2018-11-13 18:00:00"},{"dt":1542142800,"main":{"temp":9.42,"temp_min":9.42,"temp_max":9.42,"pressure":1028.31,"sea_level":1033.23,"grnd_level":1028.31,"humidity":100,"temp_kf":0},"weather":[{"id":500,"main":"Rain","description":"light rain","icon":"10n"}],"clouds":{"all":92},"wind":{"speed":7.28,"deg":245.501},"rain":{"3h":0.425},"sys":{"pod":"n"},"dt_txt":"2018-11-13 21:00:00"},{"dt":1542153600,"main":{"temp":9.5,"temp_min":9.5,"temp_max":9.5,"pressure":1028.84,"sea_level":1033.76,"grnd_level":1028.84,"humidity":100,"temp_kf":0},"weather":[{"id":500,"main":"Rain","description":"light rain","icon":"10n"}],"clouds":{"all":76},"wind":{"speed":7.26,"deg":263.001},"rain":{"3h":0.235},"sys":{"pod":"n"},"dt_txt":"2018-11-14 00:00:00"},{"dt":1542164400,"main":{"temp":9.39,"temp_min":9.39,"temp_max":9.39,"pressure":1029.28,"sea_level":1034.26,"grnd_level":1029.28,"humidity":100,"temp_kf":0},"weather":[{"id":500,"main":"Rain","description":"light rain","icon":"10n"}],"clouds":{"all":92},"wind":{"speed":7.81,"deg":273.501},"rain":{"3h":2.56},"sys":{"pod":"n"},"dt_txt":"2018-11-14 03:00:00"},{"dt":1542175200,"main":{"temp":9.8,"temp_min":9.8,"temp_max":9.8,"pressure":1030.98,"sea_level":1035.89,"grnd_level":1030.98,"humidity":99,"temp_kf":0},"weather":[{"id":500,"main":"Rain","description":"light rain","icon":"10n"}],"clouds":{"all":92},"wind":{"speed":6.72,"deg":306.003},"rain":{"3h":0.89},"sys":{"pod":"n"},"dt_txt":"2018-11-14 06:00:00"},{"dt":1542186000,"main":{"temp":10.02,"temp_min":10.02,"temp_max":10.02,"pressure":1033.47,"sea_level":1038.33,"grnd_level":1033.47,"humidity":97,"temp_kf":0},"weather":[{"id":500,"main":"Rain","description":"light rain","icon":"10d"}],"clouds":{"all":92},"wind":{"speed":6.76,"deg":305.004},"rain":{"3h":0.145},"sys":{"pod":"d"},"dt_txt":"2018-11-14 09:00:00"},{"dt":1542196800,"main":{"temp":9.97,"temp_min":9.97,"temp_max":9.97,"pressure":1035.03,"sea_level":1039.89,"grnd_level":1035.03,"humidity":97,"temp_kf":0},"weather":[{"id":500,"main":"Rain","description":"light rain","icon":"10d"}],"clouds":{"all":92},"wind":{"speed":7.59,"deg":299.504},"rain":{"3h":0.115},"sys":{"pod":"d"},"dt_txt":"2018-11-14 12:00:00"},{"dt":1542207600,"main":{"temp":9.49,"temp_min":9.49,"temp_max":9.49,"pressure":1036.18,"sea_level":1041.11,"grnd_level":1036.18,"humidity":97,"temp_kf":0},"weather":[{"id":500,"main":"Rain","description":"light rain","icon":"10n"}],"clouds":{"all":92},"wind":{"speed":6.56,"deg":293},"rain":{"3h":0.014999999999999},"sys":{"pod":"n"},"dt_txt":"2018-11-14 15:00:00"},{"dt":1542218400,"main":{"temp":9.31,"temp_min":9.31,"temp_max":9.31,"pressure":1037,"sea_level":1041.97,"grnd_level":1037,"humidity":98,"temp_kf":0},"weather":[{"id":500,"main":"Rain","description":"light rain","icon":"10n"}],"clouds":{"all":88},"wind":{"speed":5.56,"deg":288.507},"rain":{"3h":0.025},"sys":{"pod":"n"},"dt_txt":"2018-11-14 18:00:00"},{"dt":1542229200,"main":{"temp":9.35,"temp_min":9.35,"temp_max":9.35,"pressure":1037.31,"sea_level":1042.22,"grnd_level":1037.31,"humidity":98,"temp_kf":0},"weather":[{"id":500,"main":"Rain","description":"light rain","icon":"10n"}],"clouds":{"all":92},"wind":{"speed":5.11,"deg":273.505},"rain":{"3h":0.030000000000001},"sys":{"pod":"n"},"dt_txt":"2018-11-14 21:00:00"},{"dt":1542240000,"main":{"temp":9.29,"temp_min":9.29,"temp_max":9.29,"pressure":1037.67,"sea_level":1042.58,"grnd_level":1037.67,"humidity":100,"temp_kf":0},"weather":[{"id":500,"main":"Rain","description":"light rain","icon":"10n"}],"clouds":{"all":92},"wind":{"speed":4.91,"deg":259.004},"rain":{"3h":0.02},"sys":{"pod":"n"},"dt_txt":"2018-11-15 00:00:00"},{"dt":1542250800,"main":{"temp":8.97,"temp_min":8.97,"temp_max":8.97,"pressure":1037.5,"sea_level":1042.46,"grnd_level":1037.5,"humidity":100,"temp_kf":0},"weather":[{"id":500,"main":"Rain","description":"light rain","icon":"10n"}],"clouds":{"all":92},"wind":{"speed":5.21,"deg":254.505},"rain":{"3h":0.115},"sys":{"pod":"n"},"dt_txt":"2018-11-15 03:00:00"},{"dt":1542261600,"main":{"temp":8.63,"temp_min":8.63,"temp_max":8.63,"pressure":1037.55,"sea_level":1042.52,"grnd_level":1037.55,"humidity":100,"temp_kf":0},"weather":[{"id":500,"main":"Rain","description":"light rain","icon":"10n"}],"clouds":{"all":80},"wind":{"speed":5.06,"deg":242.501},"rain":{"3h":0.175},"sys":{"pod":"n"},"dt_txt":"2018-11-15 06:00:00"},{"dt":1542272400,"main":{"temp":9.05,"temp_min":9.05,"temp_max":9.05,"pressure":1038.46,"sea_level":1043.36,"grnd_level":1038.46,"humidity":100,"temp_kf":0},"weather":[{"id":500,"main":"Rain","description":"light rain","icon":"10d"}],"clouds":{"all":68},"wind":{"speed":4.66,"deg":240.507},"rain":{"3h":0.025},"sys":{"pod":"d"},"dt_txt":"2018-11-15 09:00:00"},{"dt":1542283200,"main":{"temp":10.1,"temp_min":10.1,"temp_max":10.1,"pressure":1038.91,"sea_level":1043.79,"grnd_level":1038.91,"humidity":96,"temp_kf":0},"weather":[{"id":803,"main":"Clouds","description":"broken clouds","icon":"04d"}],"clouds":{"all":68},"wind":{"speed":4.26,"deg":239.504},"rain":{},"sys":{"pod":"d"},"dt_txt":"2018-11-15 12:00:00"},{"dt":1542294000,"main":{"temp":10.15,"temp_min":10.15,"temp_max":10.15,"pressure":1039.38,"sea_level":1044.27,"grnd_level":1039.38,"humidity":95,"temp_kf":0},"weather":[{"id":803,"main":"Clouds","description":"broken clouds","icon":"04n"}],"clouds":{"all":64},"wind":{"speed":3.86,"deg":246.501},"rain":{},"sys":{"pod":"n"},"dt_txt":"2018-11-15 15:00:00"},{"dt":1542304800,"main":{"temp":9.04,"temp_min":9.04,"temp_max":9.04,"pressure":1039.64,"sea_level":1044.59,"grnd_level":1039.64,"humidity":100,"temp_kf":0},"weather":[{"id":802,"main":"Clouds","description":"scattered clouds","icon":"03n"}],"clouds":{"all":44},"wind":{"speed":4.21,"deg":242.004},"rain":{},"sys":{"pod":"n"},"dt_txt":"2018-11-15 18:00:00"},{"dt":1542315600,"main":{"temp":8.46,"temp_min":8.46,"temp_max":8.46,"pressure":1040.08,"sea_level":1045.07,"grnd_level":1040.08,"humidity":100,"temp_kf":0},"weather":[{"id":802,"main":"Clouds","description":"scattered clouds","icon":"03n"}],"clouds":{"all":44},"wind":{"speed":4.75,"deg":240.001},"rain":{},"sys":{"pod":"n"},"dt_txt":"2018-11-15 21:00:00"},{"dt":1542326400,"main":{"temp":8.3,"temp_min":8.3,"temp_max":8.3,"pressure":1040.92,"sea_level":1045.9,"grnd_level":1040.92,"humidity":100,"temp_kf":0},"weather":[{"id":801,"main":"Clouds","description":"few clouds","icon":"02n"}],"clouds":{"all":24},"wind":{"speed":4.23,"deg":243.007},"rain":{},"sys":{"pod":"n"},"dt_txt":"2018-11-16 00:00:00"},{"dt":1542337200,"main":{"temp":7.81,"temp_min":7.81,"temp_max":7.81,"pressure":1041.1,"sea_level":1046.02,"grnd_level":1041.1,"humidity":100,"temp_kf":0},"weather":[{"id":800,"main":"Clear","description":"clear sky","icon":"02n"}],"clouds":{"all":8},"wind":{"speed":4.52,"deg":242.502},"rain":{},"sys":{"pod":"n"},"dt_txt":"2018-11-16 03:00:00"},{"dt":1542348000,"main":{"temp":7.06,"temp_min":7.06,"temp_max":7.06,"pressure":1041.47,"sea_level":1046.43,"grnd_level":1041.47,"humidity":100,"temp_kf":0},"weather":[{"id":801,"main":"Clouds","description":"few clouds","icon":"02n"}],"clouds":{"all":12},"wind":{"speed":4.01,"deg":243.504},"rain":{},"sys":{"pod":"n"},"dt_txt":"2018-11-16 06:00:00"},{"dt":1542358800,"main":{"temp":8.21,"temp_min":8.21,"temp_max":8.21,"pressure":1042.32,"sea_level":1047.27,"grnd_level":1042.32,"humidity":100,"temp_kf":0},"weather":[{"id":803,"main":"Clouds","description":"broken clouds","icon":"04d"}],"clouds":{"all":64},"wind":{"speed":3.41,"deg":256.001},"rain":{},"sys":{"pod":"d"},"dt_txt":"2018-11-16 09:00:00"},{"dt":1542369600,"main":{"temp":9.44,"temp_min":9.44,"temp_max":9.44,"pressure":1042.35,"sea_level":1047.26,"grnd_level":1042.35,"humidity":97,"temp_kf":0},"weather":[{"id":803,"main":"Clouds","description":"broken clouds","icon":"04d"}],"clouds":{"all":64},"wind":{"speed":2.95,"deg":267.002},"rain":{},"sys":{"pod":"d"},"dt_txt":"2018-11-16 12:00:00"},{"dt":1542380400,"main":{"temp":9.32,"temp_min":9.32,"temp_max":9.32,"pressure":1042.2,"sea_level":1047.16,"grnd_level":1042.2,"humidity":97,"temp_kf":0},"weather":[{"id":803,"main":"Clouds","description":"broken clouds","icon":"04n"}],"clouds":{"all":64},"wind":{"speed":2.51,"deg":293.001},"rain":{},"sys":{"pod":"n"},"dt_txt":"2018-11-16 15:00:00"},{"dt":1542391200,"main":{"temp":8.68,"temp_min":8.68,"temp_max":8.68,"pressure":1042.2,"sea_level":1047.16,"grnd_level":1042.2,"humidity":100,"temp_kf":0},"weather":[{"id":803,"main":"Clouds","description":"broken clouds","icon":"04n"}],"clouds":{"all":64},"wind":{"speed":2.71,"deg":315.501},"rain":{},"sys":{"pod":"n"},"dt_txt":"2018-11-16 18:00:00"},{"dt":1542402000,"main":{"temp":7.56,"temp_min":7.56,"temp_max":7.56,"pressure":1042.5,"sea_level":1047.5,"grnd_level":1042.5,"humidity":100,"temp_kf":0},"weather":[{"id":500,"main":"Rain","description":"light rain","icon":"10n"}],"clouds":{"all":32},"wind":{"speed":2.65,"deg":338.501},"rain":{"3h":0.0050000000000008},"sys":{"pod":"n"},"dt_txt":"2018-11-16 21:00:00"},{"dt":1542412800,"main":{"temp":7.37,"temp_min":7.37,"temp_max":7.37,"pressure":1042.77,"sea_level":1047.74,"grnd_level":1042.77,"humidity":100,"temp_kf":0},"weather":[{"id":500,"main":"Rain","description":"light rain","icon":"10n"}],"clouds":{"all":88},"wind":{"speed":3.08,"deg":345.504},"rain":{"3h":0.045},"sys":{"pod":"n"},"dt_txt":"2018-11-17 00:00:00"},{"dt":1542423600,"main":{"temp":7.46,"temp_min":7.46,"temp_max":7.46,"pressure":1042.3,"sea_level":1047.34,"grnd_level":1042.3,"humidity":100,"temp_kf":0},"weather":[{"id":500,"main":"Rain","description":"light rain","icon":"10n"}],"clouds":{"all":92},"wind":{"speed":3.19,"deg":350.501},"rain":{"3h":0.115},"sys":{"pod":"n"},"dt_txt":"2018-11-17 03:00:00"},{"dt":1542434400,"main":{"temp":8.65,"temp_min":8.65,"temp_max":8.65,"pressure":1042.33,"sea_level":1047.26,"grnd_level":1042.33,"humidity":100,"temp_kf":0},"weather":[{"id":500,"main":"Rain","description":"light rain","icon":"10n"}],"clouds":{"all":92},"wind":{"speed":4.01,"deg":357.001},"rain":{"3h":0.105},"sys":{"pod":"n"},"dt_txt":"2018-11-17 06:00:00"},{"dt":1542445200,"main":{"temp":10.11,"temp_min":10.11,"temp_max":10.11,"pressure":1043.06,"sea_level":1047.95,"grnd_level":1043.06,"humidity":98,"temp_kf":0},"weather":[{"id":500,"main":"Rain","description":"light rain","icon":"10d"}],"clouds":{"all":92},"wind":{"speed":6.11,"deg":35.5019},"rain":{"3h":0.35},"sys":{"pod":"d"},"dt_txt":"2018-11-17 09:00:00"},{"dt":1542456000,"main":{"temp":9.89,"temp_min":9.89,"temp_max":9.89,"pressure":1043.43,"sea_level":1048.22,"grnd_level":1043.43,"humidity":95,"temp_kf":0},"weather":[{"id":500,"main":"Rain","description":"light rain","icon":"10d"}],"clouds":{"all":0},"wind":{"speed":6.1,"deg":37.0003},"rain":{"3h":0.029999999999999},"sys":{"pod":"d"},"dt_txt":"2018-11-17 12:00:00"}],"city":{"id":3099434,"name":"Gdansk","coord":{"lat":54.3521,"lon":18.6464},"country":"PL","population":461865}}